cnlitellm/__init__.py
cnlitellm/api.py
cnlitellm/exceptions.py
cnlitellm/models.py
cnlitellm/utils.py
cnlitellm/providers/__init__.py
cnlitellm/providers/baichuan.py
cnlitellm/providers/base_provider.py
cnlitellm/providers/coze.py
cnlitellm/providers/dify.py
cnlitellm/providers/example_provider.py
cnlitellm/providers/fastgpt.py
cnlitellm/providers/minimax.py
cnlitellm/providers/moonshot.py
cnlitellm/providers/qwen.py
cnlitellm/providers/tiangong.py
cnlitellm/providers/wenxin.py
cnlitellm/providers/xunfei.py
cnlitellm/providers/zhipu.py
tests/__init__.py
tests/test_api.py
tests/test_baichuan.py
tests/test_coze.py
tests/test_fastgpt.py
tests/test_minimax.py
tests/test_moonshot.py
tests/test_moonshot2.py
tests/test_qwen.py
tests/test_tiangong.py
tests/test_wenxin.py
tests/test_zhipu.py
tests/test_zhipu2.py
cnlitellm-0.2.5.dist-info/LICENSE
cnlitellm-0.2.5.dist-info/METADATA
cnlitellm-0.2.5.dist-info/WHEEL
cnlitellm-0.2.5.dist-info/top_level.txt
cnlitellm-0.2.5.dist-info/RECORD
