Metadata-Version: 2.1
Name: cnlitellm
Version: 0.2.5
Summary: A Python library for unified access to Chinese domestic large language models.
Home-page: https://github.com/EvalsOne/CNLiteLLM
Author: everfly
Author-email: tagriver@gmail.com
License: MIT
License-File: LICENSE
Requires-Dist: openai
Requires-Dist: pydantic
Requires-Dist: zhipuai
Requires-Dist: tenacity
Requires-Dist: dashscope
Requires-Dist: websocket-client
Requires-Dist: requests
